vhostm
