Metadata-Version: 1.1
Name: vhostm
Version: 1.1
Summary: Manage nginx virtual servers and hosts file entries.
Home-page: https://github.com/eatonphil/vhostm
Author: Phil Eaton
Author-email: me@eatonphil.com
License: UNKNOWN
Download-URL: https://github.com/eatonphil/vhostm/tarball/1.1
Keywords: nginx,virtual,hosts
Platform: UNKNOWN
